odin_bot_entities/__init__.py
odin_bot_entities/balances.py
odin_bot_entities/coin.py
odin_bot_entities/lote.py
odin_bot_entities/report.py
odin_bot_entities/trades.py
odin_bot_entities/wallet.py
odin_bot_entities-0.2.0.dist-info/WHEEL
odin_bot_entities-0.2.0.dist-info/METADATA
odin_bot_entities-0.2.0.dist-info/RECORD
